.bumpversion.cfg
CONTRIBUTING.md
LICENSE
MANIFEST.in
Makefile
README.md
pyproject.toml
setup.py
mctk/__init__.py
mctk/checking.py
mctk/models.py
mctk/tests/test_checking.py
mctk/tests/test_models.py
mctk_py.egg-info/PKG-INFO
mctk_py.egg-info/SOURCES.txt
mctk_py.egg-info/dependency_links.txt
mctk_py.egg-info/requires.txt
mctk_py.egg-info/top_level.txt