Metadata-Version: 2.1
Name: mctk-py
Version: 0.1.0
Summary: Model Checking Toolkit for Python
Author-email: marcusm117 <marcusmin117@gmail.com>
License:                                  Apache License
Project-URL: repository, https://github.com/marcusm117/mctk
Classifier: Development Status :: 2 - Pre-Alpha
Classifier: Programming Language :: Python :: Implementation :: CPython
Classifier: Programming Language :: Python :: Implementation :: PyPy
Classifier: Programming Language :: Python :: 3
Classifier: Programming Language :: Python :: 3.8
Classifier: Programming Language :: Python :: 3.9
Classifier: Programming Language :: Python :: 3.10
Classifier: Programming Language :: Python :: 3.11
Requires-Python: >=3.8
Provides-Extra: develop
License-File: LICENSE
